jstime.py
setup.py
jstime.egg-info/PKG-INFO
jstime.egg-info/SOURCES.txt
jstime.egg-info/dependency_links.txt
jstime.egg-info/top_level.txt