Metadata-Version: 1.1
Name: jstime
Version: 1.0
Summary: Convert python datatime objects to/from milliseconds from epoch
Home-page: http://github.com/LuminosoInsight/jstime
Author: Luminoso, LLC
Author-email: dev@lumino.so
License: UNKNOWN
Platform: any
Classifier: License :: OSI Approved :: MIT License
